cocomico/__init__.py
cocomico/__main__.py
cocomico/pipeline.py
cocomico/score.py
cocomico/utils.py
cocomico/encodings/score.lp
cocomico/toys/communities.json
cocomico/toys/seeds.sbml
cocomico/toys/sbml/Com1Org1.sbml
cocomico/toys/sbml/Com1Org2.sbml
cocomico/toys/sbml/Com1Org3.sbml
cocomico/toys/sbml/Com2Org1.sbml
cocomico/toys/sbml/Com2Org2.sbml
cocomico/toys/sbml/Com2Org3.sbml
cocomico/toys/sbml/Com2Org4.sbml
CoCoMiCo-0.2.1.dist-info/AUTHORS.md
CoCoMiCo-0.2.1.dist-info/LICENSE
CoCoMiCo-0.2.1.dist-info/METADATA
CoCoMiCo-0.2.1.dist-info/WHEEL
CoCoMiCo-0.2.1.dist-info/entry_points.txt
CoCoMiCo-0.2.1.dist-info/top_level.txt
CoCoMiCo-0.2.1.dist-info/RECORD
