Metadata-Version: 2.1
Name: CoCoMiCo
Version: 0.2.1
Summary: COoperation and COmpetition potentials in MIcrobial COmunities
Home-page: https://gitlab.inria.fr/ccmc/CoCoMiCo
Author: Maxime lecomte
Author-email: maxime.lecomte@inria.fr,clemence.frioux@inria.fr
License: GPLv3+
Project-URL: Issue Tracker, https://gitlab.inria.fr/CCMC/CoCoMiCo/issues
Keywords: microbial communities,bioinformatics
Classifier: Programming Language :: Python :: 3.7
Classifier: Programming Language :: Python :: 3.8
Classifier: Programming Language :: Python :: 3.9
Classifier: Operating System :: MacOS :: MacOS X
Classifier: Operating System :: Unix
Requires-Python: >=3.8
License-File: LICENSE
License-File: AUTHORS.md
Requires-Dist: clyngor-with-clingo
Requires-Dist: pandas
Requires-Dist: matplotlib
